{
  "红色警戒": "红色警报",
  "红色警报处于活动状态时请勿执行中心活动": "红色警报出现时不要执行基地活动",
  "禁用红色警报寻路": "禁用前往红色警报的寻路",
  "使用红色警戒 NPC 出行": "使用红色警报 NPC 传送",
  "遗迹模式：允许红色警报": "遗物工具模式：允许红色警报",
  "遗迹模式：仅启用": "遗物工具模式：仅已启用",
  "临时代表团": "临时探索任务",
  "临时任务[天气/时间/顺序]": "临时探索任务 [天气/限时/连续]",
  "临时：类型订单": "临时探索：类型顺序",
  "临时：职业订单": "临时探索：职业顺序",
  "临时：允许所有类别": "临时探索：允许所有职业",
  "临时职业优先": "临时探索职业优先级",
  "允许所有临时职业": "允许所有职业参与临时探索任务",
  "序列任务": "连续任务",
  "关键区域": "紧急任务区域",
  "关键位置": "紧急任务位置",
  "关键任务": "紧急任务",
  "关键：允许所有类": "紧急任务：允许所有职业",
  "当前是临界任务，应直接交付。": "当前是紧急任务，应直接交付。",
  "临界任务拿分收益通常都值得做。": "紧急任务通常很适合拿分。",
  "只要能做，临界任务通常都值得优先做来拿分。": "只要能做，紧急任务通常值得优先刷分。",
  "黄金完成": "金牌完成",
  "黄金完成后删除任务": "金牌完成后移除任务",
  "黄金完成模式": "金牌完成模式",
  "黄金需求": "金牌需求",
  "黄金序列": "金星连锁",
  "当您在当前月球上所选职业的每一项非临时、非关键任务都是黄金时停止。\n定时任务、天气任务、顺序任务和红色警报任务不计算在内。": "当前星球上所选职业的所有基础探索任务都取得金牌后停止。\n限时、天气、连续和红色警报任务不计入。",
  "您想运行自动无人机查找吗？如果是，请启用此功能\n请注意。做。不是。离开。这。独自的。这仍在大力研究中": "是否启用自动寻找无人机位置？\n注意：不要无人看管地运行。此功能仍在大量调整中。",
  "您什么时候想从供应商那里购买无人机？\n设置增量为 200，最多 5,000": "无人机位元达到多少时从商人处购买无人机？\n以 200 为增量设置，最高 5,000。",
  "在与以太碎片/红色警报 npc 旅行交互之前添加随机延迟。\n延迟将发生在与菜单交互之前和中间": "与以太碎晶或红色警报传送 NPC 交互前加入随机延迟。\n延迟会加在打开菜单前，以及菜单交互之间。",
  "为以太网/NPC 旅行添加延迟": "为以太碎晶/NPC 传送添加延迟",
  "旅行与寻路": "传送与寻路",
  "除中心活动外": "除基地活动外",
  "中心活动": "基地活动",
  "自动化中心活动": "自动执行基地活动",
  "获取当前中心预测": "获取当前基地预报",
  "任务不是一次聚会或关键任务。导航网格移动是没有必要的。进入下一步": "任务不是采集或紧急任务，不需要 navmesh 移动，进入下一步。",
  "我们目前的目标是完成一项关键任务，而且我们是一名工匠（？），所以我们不会离开我们的位置": "当前目标是紧急任务，且当前职业是制作职业，因此不离开当前位置。",
  "这将允许你磨练其他类别的批评/红色警报。 （因此，如果您使用 crp，但会弹出 bsm 红色警报）": "允许为其他职业刷紧急任务/红色警报。（例如你当前是木工，但刷新了锻铁匠的红色警报）",
  "如果选择了多个任务并且启用了执行多个课程的选项，则您想要执行临时任务的顺序": "选择多个任务且启用多职业时，临时探索任务的执行顺序。",
  "农业特定课程分数达到 500k": "将指定职业刷到 50 万分",
  "将选定的课程升级到特定级别": "将选定职业升到指定等级",
  "具体课程详情": "指定职业详情",
  "课程进度：全部": "职业进度：全部",
  "课程进度：图标预览": "职业进度：图标预览",
  "所有课程": "所有职业",
  "类别选择表": "职业选择表",
  "适用于所有类别": "适用于所有职业",
  "适用于特定类别": "适用于指定职业",
  "已完成所有类别的文物": "所有职业遗物工具已完成",
  "将类别切换到 CRP": "切换职业到 CRP",
  "将类别切换为 MIN": "切换职业到 MIN",
  "WKS 开关类别选项卡": "WKS 切换职业标签页",
  "测试无人机 购买": "测试购买无人机",
  "测试无人机 购买物品": "测试购买无人机物品"
}
